pyexcel_io/__init__.py
pyexcel_io/_compact.py
pyexcel_io/book.py
pyexcel_io/constants.py
pyexcel_io/exceptions.py
pyexcel_io/io.py
pyexcel_io/manager.py
pyexcel_io/plugins.py
pyexcel_io/reader.py
pyexcel_io/service.py
pyexcel_io/sheet.py
pyexcel_io/utils.py
pyexcel_io/writer.py
pyexcel_io/database/__init__.py
pyexcel_io/database/common.py
pyexcel_io/database/querysets.py
pyexcel_io/database/exporters/__init__.py
pyexcel_io/database/exporters/django.py
pyexcel_io/database/exporters/queryset.py
pyexcel_io/database/exporters/sqlalchemy.py
pyexcel_io/database/importers/__init__.py
pyexcel_io/database/importers/django.py
pyexcel_io/database/importers/sqlalchemy.py
pyexcel_io/plugin_api/__init__.py
pyexcel_io/plugin_api/abstract_reader.py
pyexcel_io/plugin_api/abstract_sheet.py
pyexcel_io/plugin_api/abstract_writer.py
pyexcel_io/readers/__init__.py
pyexcel_io/readers/csv_content.py
pyexcel_io/readers/csv_in_file.py
pyexcel_io/readers/csv_in_memory.py
pyexcel_io/readers/csv_sheet.py
pyexcel_io/readers/csvz.py
pyexcel_io/writers/__init__.py
pyexcel_io/writers/csv_in_file.py
pyexcel_io/writers/csv_in_memory.py
pyexcel_io/writers/csv_sheet.py
pyexcel_io/writers/csvz_sheet.py
pyexcel_io/writers/csvz_writer.py
pyexcel_io-0.6.7.dist-info/LICENSE
pyexcel_io-0.6.7.dist-info/METADATA
pyexcel_io-0.6.7.dist-info/WHEEL
pyexcel_io-0.6.7.dist-info/top_level.txt
pyexcel_io-0.6.7.dist-info/RECORD
