Metadata-Version: 2.1
Name: pyexcel-io
Version: 0.6.7
Summary: A python library to read and write structured data in csv, zipped csvformat and to/from databases
Home-page: https://github.com/pyexcel/pyexcel-io
Download-URL: https://github.com/pyexcel/pyexcel-io/archive/0.6.7.tar.gz
Author: C.W.
Author-email: info@pyexcel.org
License: New BSD
Keywords: python,API,tsv,tsvz,csv,csvz,django,sqlalchemy
Classifier: Topic :: Software Development :: Libraries
Classifier: Programming Language :: Python
Classifier: Intended Audience :: Developers
Classifier: Programming Language :: Python :: 3 :: Only
Classifier: Programming Language :: Python :: 3.6
Classifier: Programming Language :: Python :: 3.7
Classifier: Programming Language :: Python :: 3.8
Classifier: License :: OSI Approved :: BSD License
Classifier: Programming Language :: Python :: Implementation :: PyPy
Requires-Python: >=3.6
License-File: LICENSE
Requires-Dist: lml>=0.0.4
Provides-Extra: extra
Requires-Dist: chardet; extra == "extra"
Provides-Extra: xls
Requires-Dist: pyexcel-xls>=0.6.0; extra == "xls"
Provides-Extra: xlsx
Requires-Dist: pyexcel-xlsx>=0.6.0; extra == "xlsx"
Provides-Extra: ods
Requires-Dist: pyexcel-ods3>=0.6.0; extra == "ods"
